{"State Start Year": {"CA": 2018, "NY": 2018, "IL": 2023, "MA": 2023, "MI": 2023, "FL": 2023, "AL": 2025, "AR": 2025, "AZ": 2025, "CO": 2025, "CT": 2025, "DC": 2025, "DE": 2025, "GA": 2025, "IA": 2025, "ID": 2025, "IN": 2025, "KS": 2025, "KY": 2025, "LA": 2025, "MD": 2025, "ME": 2025, "MN": 2025, "MO": 2025, "MS": 2025, "MT": 2025, "NC": 2025, "ND": 2025, "NE": 2025, "NH": 2025, "NJ": 2025, "NM": 2025, "NV": 2025, "OH": 2025, "OK": 2025, "OR": 2025, "PA": 2025, "RI": 2025, "SC": 2025, "SD": 2025, "TN": 2025, "TX": 2025, "UT": 2025, "VA": 2025, "VT": 2025, "WA": 2025, "WI": 2025, "WV": 2025, "WY": 2025}, "State Target Year": {"NY": 2040, "CA": 2045, "IL": 2050, "OH": 2050, "MI": 2050, "TX": 2050, "PA": 2050, "MA": 2050, "FL": 2050, "AL": 2050, "AR": 2050, "AZ": 2050, "CO": 2050, "CT": 2050, "DC": 2050, "DE": 2050, "GA": 2050, "IA": 2050, "ID": 2050, "IN": 2050, "KS": 2050, "KY": 2050, "LA": 2050, "MD": 2050, "ME": 2050, "MN": 2050, "MO": 2050, "MS": 2050, "MT": 2050, "NC": 2050, "ND": 2050, "NE": 2050, "NH": 2050, "NJ": 2050, "NM": 2050, "NV": 2050, "OK": 2050, "OR": 2050, "RI": 2050, "SC": 2050, "SD": 2050, "TN": 2050, "UT": 2050, "VA": 2050, "VT": 2050, "WA": 2050, "WI": 2050, "WV": 2050, "WY": 2050}, "State Timezone": {"AL": "CST", "AR": "CST", "AZ": "MST", "CA": "PST", "CO": "MST", "CT": "EST", "DC": "EST", "DE": "EST", "FL": "EST", "GA": "EST", "IA": "CST", "ID": "MST", "IL": "CST", "IN": "EST", "KS": "CST", "KY": "CST", "LA": "CST", "MA": "EST", "MD": "EST", "ME": "EST", "MI": "EST", "MN": "CST", "MO": "CST", "MS": "CST", "MT": "MST", "NC": "EST", "ND": "CST", "NE": "CST", "NH": "EST", "NJ": "EST", "NM": "MST", "NV": "PST", "NY": "EST", "OH": "EST", "OK": "CST", "OR": "PST", "PA": "EST", "RI": "EST", "SC": "EST", "SD": "CST", "TN": "CST", "TX": "CST", "UT": "MST", "VA": "EST", "VT": "EST", "WA": "PST", "WI": "CST", "WV": "EST", "WY": "MST"}, "State Heater Year": {"CA": 2030, "NY": 2030, "IL": 2036, "OH": 2036, "MI": 2036, "TX": 2036, "PA": 2036, "MA": 2036, "FL": 2036, "AL": 2036, "AR": 2036, "AZ": 2036, "CO": 2036, "CT": 2036, "DC": 2036, "DE": 2036, "GA": 2036, "IA": 2036, "ID": 2036, "IN": 2036, "KS": 2036, "KY": 2036, "LA": 2036, "MD": 2036, "ME": 2036, "MN": 2036, "MO": 2036, "MS": 2036, "MT": 2036, "NC": 2036, "ND": 2036, "NE": 2036, "NH": 2036, "NJ": 2036, "NM": 2036, "NV": 2036, "OK": 2036, "OR": 2036, "RI": 2036, "SC": 2036, "SD": 2036, "TN": 2036, "UT": 2036, "VA": 2036, "VT": 2036, "WA": 2036, "WI": 2036, "WV": 2036, "WY": 2036}, "State Water Year": {"CA": 2030, "NY": 2030, "IL": 2036, "OH": 2036, "MI": 2036, "TX": 2036, "PA": 2036, "MA": 2036, "FL": 2036, "AL": 2036, "AR": 2036, "AZ": 2036, "CO": 2036, "CT": 2036, "DC": 2036, "DE": 2036, "GA": 2036, "IA": 2036, "ID": 2036, "IN": 2036, "KS": 2036, "KY": 2036, "LA": 2036, "MD": 2036, "ME": 2036, "MN": 2036, "MO": 2036, "MS": 2036, "MT": 2036, "NC": 2036, "ND": 2036, "NE": 2036, "NH": 2036, "NJ": 2036, "NM": 2036, "NV": 2036, "OK": 2036, "OR": 2036, "RI": 2036, "SC": 2036, "SD": 2036, "TN": 2036, "UT": 2036, "VA": 2036, "VT": 2036, "WA": 2036, "WI": 2036, "WV": 2036, "WY": 2036}, "State Clothes Year": {"CA": 2030, "NY": 2030, "IL": 2036, "OH": 2036, "MI": 2036, "TX": 2036, "PA": 2036, "MA": 2036, "FL": 2036, "AL": 2036, "AR": 2036, "AZ": 2036, "CO": 2036, "CT": 2036, "DC": 2036, "DE": 2036, "GA": 2036, "IA": 2036, "ID": 2036, "IN": 2036, "KS": 2036, "KY": 2036, "LA": 2036, "MD": 2036, "ME": 2036, "MN": 2036, "MO": 2036, "MS": 2036, "MT": 2036, "NC": 2036, "ND": 2036, "NE": 2036, "NH": 2036, "NJ": 2036, "NM": 2036, "NV": 2036, "OK": 2036, "OR": 2036, "RI": 2036, "SC": 2036, "SD": 2036, "TN": 2036, "UT": 2036, "VA": 2036, "VT": 2036, "WA": 2036, "WI": 2036, "WV": 2036, "WY": 2036}, "State Cooking Year": {"CA": 2030, "NY": 2030, "IL": 2036, "OH": 2036, "MI": 2036, "TX": 2036, "PA": 2036, "MA": 2036, "FL": 2036, "AL": 2036, "AR": 2036, "AZ": 2036, "CO": 2036, "CT": 2036, "DC": 2036, "DE": 2036, "GA": 2036, "IA": 2036, "ID": 2036, "IN": 2036, "KS": 2036, "KY": 2036, "LA": 2036, "MD": 2036, "ME": 2036, "MN": 2036, "MO": 2036, "MS": 2036, "MT": 2036, "NC": 2036, "ND": 2036, "NE": 2036, "NH": 2036, "NJ": 2036, "NM": 2036, "NV": 2036, "OK": 2036, "OR": 2036, "RI": 2036, "SC": 2036, "SD": 2036, "TN": 2036, "UT": 2036, "VA": 2036, "VT": 2036, "WA": 2036, "WI": 2036, "WV": 2036, "WY": 2036}, "State Heater AR": {"CA": 50, "NY": 50, "IL": 50, "OH": 50, "MI": 50, "TX": 50, "PA": 50, "MA": 50, "FL": 50, "AL": 50, "AR": 50, "AZ": 50, "CO": 50, "CT": 50, "DC": 50, "DE": 50, "GA": 50, "IA": 50, "ID": 50, "IN": 50, "KS": 50, "KY": 50, "LA": 50, "MD": 50, "ME": 50, "MN": 50, "MO": 50, "MS": 50, "MT": 50, "NC": 50, "ND": 50, "NE": 50, "NH": 50, "NJ": 50, "NM": 50, "NV": 50, "OK": 50, "OR": 50, "RI": 50, "SC": 50, "SD": 50, "TN": 50, "UT": 50, "VA": 50, "VT": 50, "WA": 50, "WI": 50, "WV": 50, "WY": 50}, "State Water AR": {"CA": 50, "NY": 50, "IL": 50, "OH": 50, "MI": 50, "TX": 50, "PA": 50, "MA": 50, "FL": 50, "AL": 50, "AR": 50, "AZ": 50, "CO": 50, "CT": 50, "DC": 50, "DE": 50, "GA": 50, "IA": 50, "ID": 50, "IN": 50, "KS": 50, "KY": 50, "LA": 50, "MD": 50, "ME": 50, "MN": 50, "MO": 50, "MS": 50, "MT": 50, "NC": 50, "ND": 50, "NE": 50, "NH": 50, "NJ": 50, "NM": 50, "NV": 50, "OK": 50, "OR": 50, "RI": 50, "SC": 50, "SD": 50, "TN": 50, "UT": 50, "VA": 50, "VT": 50, "WA": 50, "WI": 50, "WV": 50, "WY": 50}, "State Clothes AR": {"CA": 50, "NY": 50, "IL": 50, "OH": 50, "MI": 50, "TX": 50, "PA": 50, "MA": 50, "FL": 50, "AL": 50, "AR": 50, "AZ": 50, "CO": 50, "CT": 50, "DC": 50, "DE": 50, "GA": 50, "IA": 50, "ID": 50, "IN": 50, "KS": 50, "KY": 50, "LA": 50, "MD": 50, "ME": 50, "MN": 50, "MO": 50, "MS": 50, "MT": 50, "NC": 50, "ND": 50, "NE": 50, "NH": 50, "NJ": 50, "NM": 50, "NV": 50, "OK": 50, "OR": 50, "RI": 50, "SC": 50, "SD": 50, "TN": 50, "UT": 50, "VA": 50, "VT": 50, "WA": 50, "WI": 50, "WV": 50, "WY": 50}, "State Cooking AR": {"CA": 50, "NY": 50, "IL": 50, "OH": 50, "MI": 50, "TX": 50, "PA": 50, "MA": 50, "FL": 50, "AL": 50, "AR": 50, "AZ": 50, "CO": 50, "CT": 50, "DC": 50, "DE": 50, "GA": 50, "IA": 50, "ID": 50, "IN": 50, "KS": 50, "KY": 50, "LA": 50, "MD": 50, "ME": 50, "MN": 50, "MO": 50, "MS": 50, "MT": 50, "NC": 50, "ND": 50, "NE": 50, "NH": 50, "NJ": 50, "NM": 50, "NV": 50, "OK": 50, "OR": 50, "RI": 50, "SC": 50, "SD": 50, "TN": 50, "UT": 50, "VA": 50, "VT": 50, "WA": 50, "WI": 50, "WV": 50, "WY": 50}, "State Cooling Year": {"CA": 2030, "NY": 2030, "AL": 2036, "AR": 2036, "AZ": 2036, "CO": 2036, "CT": 2036, "DC": 2036, "DE": 2036, "FL": 2036, "GA": 2036, "IA": 2036, "ID": 2036, "IL": 2036, "IN": 2036, "KS": 2036, "KY": 2036, "LA": 2036, "MA": 2036, "MD": 2036, "ME": 2036, "MI": 2036, "MN": 2036, "MO": 2036, "MS": 2036, "MT": 2036, "NC": 2036, "ND": 2036, "NE": 2036, "NH": 2036, "NJ": 2036, "NM": 2036, "NV": 2036, "OH": 2036, "OK": 2036, "OR": 2036, "PA": 2036, "RI": 2036, "SC": 2036, "SD": 2036, "TN": 2036, "TX": 2036, "UT": 2036, "VA": 2036, "VT": 2036, "WA": 2036, "WI": 2036, "WV": 2036, "WY": 2036}, "State Interior Equipment Year": {"CA": 2030, "NY": 2030, "AL": 2036, "AR": 2036, "AZ": 2036, "CO": 2036, "CT": 2036, "DC": 2036, "DE": 2036, "FL": 2036, "GA": 2036, "IA": 2036, "ID": 2036, "IL": 2036, "IN": 2036, "KS": 2036, "KY": 2036, "LA": 2036, "MA": 2036, "MD": 2036, "ME": 2036, "MI": 2036, "MN": 2036, "MO": 2036, "MS": 2036, "MT": 2036, "NC": 2036, "ND": 2036, "NE": 2036, "NH": 2036, "NJ": 2036, "NM": 2036, "NV": 2036, "OH": 2036, "OK": 2036, "OR": 2036, "PA": 2036, "RI": 2036, "SC": 2036, "SD": 2036, "TN": 2036, "TX": 2036, "UT": 2036, "VA": 2036, "VT": 2036, "WA": 2036, "WI": 2036, "WV": 2036, "WY": 2036}, "State Cooling AR": {"AL": 50, "AR": 50, "AZ": 50, "CA": 50, "CO": 50, "CT": 50, "DC": 50, "DE": 50, "FL": 50, "GA": 50, "IA": 50, "ID": 50, "IL": 50, "IN": 50, "KS": 50, "KY": 50, "LA": 50, "MA": 50, "MD": 50, "ME": 50, "MI": 50, "MN": 50, "MO": 50, "MS": 50, "MT": 50, "NC": 50, "ND": 50, "NE": 50, "NH": 50, "NJ": 50, "NM": 50, "NV": 50, "NY": 50, "OH": 50, "OK": 50, "OR": 50, "PA": 50, "RI": 50, "SC": 50, "SD": 50, "TN": 50, "TX": 50, "UT": 50, "VA": 50, "VT": 50, "WA": 50, "WI": 50, "WV": 50, "WY": 50}, "State Interior Equipment AR": {"AL": 50, "AR": 50, "AZ": 50, "CA": 50, "CO": 50, "CT": 50, "DC": 50, "DE": 50, "FL": 50, "GA": 50, "IA": 50, "ID": 50, "IL": 50, "IN": 50, "KS": 50, "KY": 50, "LA": 50, "MA": 50, "MD": 50, "ME": 50, "MI": 50, "MN": 50, "MO": 50, "MS": 50, "MT": 50, "NC": 50, "ND": 50, "NE": 50, "NH": 50, "NJ": 50, "NM": 50, "NV": 50, "NY": 50, "OH": 50, "OK": 50, "OR": 50, "PA": 50, "RI": 50, "SC": 50, "SD": 50, "TN": 50, "TX": 50, "UT": 50, "VA": 50, "VT": 50, "WA": 50, "WI": 50, "WV": 50, "WY": 50}}